LICENSE.md
MANIFEST.in
README.md
setup.py
hass_frontend/__init__.py
hass_frontend/authorize.html
hass_frontend/index.html
hass_frontend/onboarding.html
hass_frontend/robots.txt
hass_frontend/service_worker.js
hass_frontend/frontend_es5/384d56614b5f557b6315.worker.js
hass_frontend/frontend_es5/384d56614b5f557b6315.worker.js.gz
hass_frontend/frontend_es5/384d56614b5f557b6315.worker.js.map
hass_frontend/frontend_es5/app.bf18ba88.js
hass_frontend/frontend_es5/app.bf18ba88.js.LICENSE
hass_frontend/frontend_es5/app.bf18ba88.js.gz
hass_frontend/frontend_es5/app.bf18ba88.js.map
hass_frontend/frontend_es5/authorize.9985c378.js
hass_frontend/frontend_es5/authorize.9985c378.js.LICENSE
hass_frontend/frontend_es5/authorize.9985c378.js.gz
hass_frontend/frontend_es5/authorize.9985c378.js.map
hass_frontend/frontend_es5/chunk.029fd9aec3a8c0b64e6b.js
hass_frontend/frontend_es5/chunk.029fd9aec3a8c0b64e6b.js.gz
hass_frontend/frontend_es5/chunk.029fd9aec3a8c0b64e6b.js.map
hass_frontend/frontend_es5/chunk.035bef5695902ddb8af6.js
hass_frontend/frontend_es5/chunk.035bef5695902ddb8af6.js.LICENSE
hass_frontend/frontend_es5/chunk.035bef5695902ddb8af6.js.gz
hass_frontend/frontend_es5/chunk.035bef5695902ddb8af6.js.map
hass_frontend/frontend_es5/chunk.03cb91c7df20933bd3c1.js
hass_frontend/frontend_es5/chunk.03cb91c7df20933bd3c1.js.LICENSE
hass_frontend/frontend_es5/chunk.03cb91c7df20933bd3c1.js.gz
hass_frontend/frontend_es5/chunk.03cb91c7df20933bd3c1.js.map
hass_frontend/frontend_es5/chunk.05c2ceeebe0780c0cff0.js
hass_frontend/frontend_es5/chunk.05c2ceeebe0780c0cff0.js.LICENSE
hass_frontend/frontend_es5/chunk.05c2ceeebe0780c0cff0.js.gz
hass_frontend/frontend_es5/chunk.05c2ceeebe0780c0cff0.js.map
hass_frontend/frontend_es5/chunk.069b83f713d566240efd.js
hass_frontend/frontend_es5/chunk.069b83f713d566240efd.js.gz
hass_frontend/frontend_es5/chunk.069b83f713d566240efd.js.map
hass_frontend/frontend_es5/chunk.06b878a686af0568a107.js
hass_frontend/frontend_es5/chunk.06b878a686af0568a107.js.LICENSE
home_assistant_frontend.egg-info/PKG-INFO
home_assistant_frontend.egg-info/SOURCES.txt
home_assistant_frontend.egg-info/dependency_links.txt
home_assistant_frontend.egg-info/not-zip-safe
home_assistant_frontend.egg-info/top_level.txt