Metadata-Version: 1.0
Name: home-assistant-frontend
Version: 20200509.0
Summary: The Home Assistant frontend
Home-page: https://github.com/home-assistant/home-assistant-polymer
Author: The Home Assistant Authors
Author-email: hello@home-assistant.io
License: Apache License 2.0
Platform: UNKNOWN
